alibabacloud_aiworkspace20210204/__init__.py
alibabacloud_aiworkspace20210204/client.py
alibabacloud_aiworkspace20210204/models/__init__.py
alibabacloud_aiworkspace20210204/models/_accept_dataworks_event_request.py
alibabacloud_aiworkspace20210204/models/_accept_dataworks_event_response.py
alibabacloud_aiworkspace20210204/models/_accept_dataworks_event_response_body.py
alibabacloud_aiworkspace20210204/models/_add_image_labels_request.py
alibabacloud_aiworkspace20210204/models/_add_image_labels_response.py
alibabacloud_aiworkspace20210204/models/_add_image_labels_response_body.py
alibabacloud_aiworkspace20210204/models/_add_image_request.py
alibabacloud_aiworkspace20210204/models/_add_image_response.py
alibabacloud_aiworkspace20210204/models/_add_image_response_body.py
alibabacloud_aiworkspace20210204/models/_add_member_role_response.py
alibabacloud_aiworkspace20210204/models/_add_member_role_response_body.py
alibabacloud_aiworkspace20210204/models/_change_resource_group_request.py
alibabacloud_aiworkspace20210204/models/_change_resource_group_response.py
alibabacloud_aiworkspace20210204/models/_change_resource_group_response_body.py
alibabacloud_aiworkspace20210204/models/_code_source_item.py
alibabacloud_aiworkspace20210204/models/_collection.py
alibabacloud_aiworkspace20210204/models/_connection.py
alibabacloud_aiworkspace20210204/models/_create_code_source_request.py
alibabacloud_aiworkspace20210204/models/_create_code_source_response.py
alibabacloud_aiworkspace20210204/models/_create_code_source_response_body.py
alibabacloud_aiworkspace20210204/models/_create_connection_request.py
alibabacloud_aiworkspace20210204/models/_create_connection_response.py
alibabacloud_aiworkspace20210204/models/_create_connection_response_body.py
alibabacloud_aiworkspace20210204/models/_create_dataset_file_metas_request.py
alibabacloud_aiworkspace20210204/models/_create_dataset_file_metas_response.py
alibabacloud_aiworkspace20210204/models/_create_dataset_file_metas_response_body.py
alibabacloud_aiworkspace20210204-8.0.3.dist-info/LICENSE
alibabacloud_aiworkspace20210204-8.0.3.dist-info/METADATA
alibabacloud_aiworkspace20210204-8.0.3.dist-info/WHEEL
alibabacloud_aiworkspace20210204-8.0.3.dist-info/top_level.txt
alibabacloud_aiworkspace20210204-8.0.3.dist-info/RECORD
